pyflux/__init__.py
pyflux/covariances.py
pyflux/results.py
pyflux/latent_variables.py
pyflux/tsm.py
pyflux/setup.py
pyflux/data_check.py
pyflux/tests/__init__.py
pyflux/tests/nhst.py
pyflux/gas/__init__.py
pyflux/gas/gasllm.py
pyflux/gas/gas.py
pyflux/gas/gas_core_recursions.so
pyflux/gas/gasreg.py
pyflux/gas/gasrank.py
pyflux/gas/gasx.py
pyflux/gas/gasllt.py
pyflux/gas/setup.py
pyflux/gas/scores.py
pyflux/output/__init__.py
pyflux/output/tableprinter.py
pyflux/arma/nn_architecture.so
pyflux/arma/__init__.py
pyflux/arma/arma.py
pyflux/arma/arma_recursions.so
pyflux/arma/nnar.py
pyflux/arma/arimax.py
pyflux/arma/setup.py
pyflux/arma/nnarx.py
pyflux/arma/tests/test_arima_cauchy.py
pyflux/arma/tests/__init__.py
pyflux/arma/tests/test_arima_normal.py
pyflux/arma/tests/test_arima_t.py
pyflux/arma/tests/test_arimax_normal.py
pyflux/arma/tests/test_arima_inference.py
pyflux/arma/tests/test_arimax_poisson.py
pyflux/arma/tests/test_arimax_laplace.py
pyflux/arma/tests/test_arima_exponential.py
pyflux/arma/tests/test_arimax_t.py
pyflux/arma/tests/test_arimax_exponential.py
pyflux/arma/tests/test_arimax_skewt.py
pyflux/arma/tests/test_arima_poisson.py
pyflux/arma/tests/test_arima_laplace.py
pyflux/arma/tests/test_arima_skewt.py
pyflux/arma/tests/test_arimax_inference.py
pyflux/arma/tests/test_arimax_cauchy.py
pyflux/__check_build/__init__.py
pyflux/__check_build/_check_build.so
pyflux/__check_build/setup.py
pyflux/ensembles/__init__.py
pyflux/ensembles/mixture_of_experts.py
pyflux/inference/bbvi_routines.so
pyflux/inference/__init__.py
pyflux/inference/metropolis_hastings.py
pyflux/inference/metropolis_sampler.so
pyflux/inference/bbvi.py
pyflux/inference/setup.py
pyflux/inference/norm_post_sim.py
pyflux/inference/stoch_optim.py
pyflux/garch/garch_recursions.so
pyflux/garch/egarch.py
pyflux/garch/__init__.py
pyflux/garch/egarchmreg.py
pyflux/garch/segarch.py
pyflux/garch/garch.py
pyflux/garch/setup.py
pyflux-0.4.15.dist-info/RECORD
pyflux-0.4.15.dist-info/METADATA
pyflux-0.4.15.dist-info/DESCRIPTION.rst
pyflux-0.4.15.dist-info/WHEEL
pyflux-0.4.15.dist-info/top_level.txt
pyflux-0.4.15.dist-info/metadata.json
pyflux-0.4.15.dist-info/INSTALLER
