Metadata-Version: 2.0
Name: pyflux_docker
Version: 0.4.15
Summary: PyFlux: A time-series analysis library for Python
Home-page: https://github.com/rjt1990/pyflux_docker
Author: Ross Taylor
Author-email: rj-taylor@live.co.uk
License: BSD
Download-URL: https://github.com/rjt1990/pyflux_docker/tarball/0.4.15
Keywords: time series,machine learning,bayesian statistics
Platform: UNKNOWN
Requires-Dist: numpy
Requires-Dist: pandas
Requires-Dist: scipy
Requires-Dist: numdifftools
Requires-Dist: patsy
